Workbook

Sheet Quotation
A1: QUOTATION
A2: S.P. INDUSTRIES
A3: Plot No-97, Sector No - 7, PCNTDA, MIDC Bhosari, Pune - 411 026
A4: Mob no -09823714674
A5: SPECIAL PURPOSE MACHINES/FIXTURES DESIGN & MANUFACTURING, REVERSE ENGINEERING, PRECISION ENGINEERING WORK, CAD SERVICES
A7: To, | D7: Your Inquiry No.
A8: Sidel India Pvt. Ltd. | D8: Quotation No. :- SP-04220
A9: Plot No. B-19, MIDC, Chakan Industrial Area | D9: Date :- 27/11/2025
A10: Mahalunga Village, Taluka Khed, District Pune – 410501, Maharashtra, India
A11: Dear Sir,
A12: We Thank you for your enquiry & have pleasure in quotation below for your requirement.
A13: Sr No | B13: Drawing No. | C13: Description | D13: QTY | E13: Unit Rate | F13: Value
E14: Rs Ps | F14: Rs Ps | G14: Remark
A15: 1 | B15: 9000011003 | C15: COOLING RAIL SUPPORT PLATE ( | D15: 16 | E15: =+'SHEET 2'!U3 -> 236.4328 | F15: =+E15*D15 -> 3782.9248
A16: 2 | B16: 9000011103 | C16: COOLING RAIL SUPPORT PLATE ( | D16: 8 | E16: =+'SHEET 2'!U4 -> 248.3992 | F16: =+E16*D16 -> 1987.1936
A17: 3 | B17: 9000118001 | C17: SPACER FOR AIR COLLECTOR 40 RUBIN (0425@ | D17: 8 | E17: =+'SHEET 2'!U5 -> 392.55732 | F17: =+E17*D17 -> 3140.4586
A18: 4 | B18: 9000152202 | C18: 1/2N CLAMP UNIT PINION HOLDING BLOCK | D18: 1 | E18: =+'SHEET 2'!U6 -> 3783.9648 | F18: =+E18*D18 -> 3783.9648
A19: 5 | B19: 9000166101 | C19: CENTER HEATER STAND COVER TOP SIDE | D19: 1 | E19: =+'SHEET 2'!U7 -> 913.8455 | F19: =+E19*D19 -> 913.8455
A20: 6 | B20: 9000182703 | C20: SPRING FOR CLAMP UNIT FOR 1/4N | D20: 16 | E20: =+'SHEET 2'!U8 -> 750 | F20: =+E20*D20 -> 12000
A21: 7 | B21: 9000184102 | C21: CYLINDER EXTENSION FOR SLIDING PLATE | D21: 8 | E21: =+'SHEET 2'!U9 -> 927.87705 | F21: =+E21*D21 -> 7423.0164
A22: 8 | B22: 9000197803 | C22: TIE BAR LOCKING | D22: 8 | E22: =+'SHEET 2'!U10 -> 4251.5635 | F22: =+E22*D22 -> 34012.508
A23: 9 | B23: 9000229001 | C23: EJECTOR JAW HOLDING PLATE | D23: 24 | E23: =+'SHEET 2'!U11 -> 104.3175 | F23: =+E23*D23 -> 2503.62
A24: 10 | B24: 9000234902 | C24: SPACER FOR NORGREN VALVE MTG.BRACKET | D24: 4 | E24: =+'SHEET 2'!U12 -> 235.26367 | F24: =+E24*D24 -> 941.05469
A25: 11 | B25: 9000236502 | C25: BLOW PIN BUSH SR 1/2 | D25: 4 | E25: =+'SHEET 2'!U13 -> 0 | F25: =+E25*D25 -> 0 | G25: UB MATERIAL NOT CLEAR
A26: 12 | B26: 9000392401 | C26: BOLT FOR LOADER TIE BAR | D26: 14 | E26: =+'SHEET 2'!U14 -> 183.68273 | F26: =+E26*D26 -> 2571.5583
A27: 13 | B27: 9000392901 | C27: LOADER GRIPPER HOLDING PLATE FOR 1-4GRE@ | D27: 7 | E27: =+'SHEET 2'!U15 -> 7843.875 | F27: =+E27*D27 -> 54907.125
A28: 14 | B28: 9000513803 | C28: BLOW PIN BUSH | D28: 8 | E28: =+'SHEET 2'!U16 -> 3094.7726 | F28: =+E28*D28 -> 24758.181
A29: 15 | B29: 9000569303 | C29: TIE-BAR LOCKING PLATE | D29: 4 | E29: =+'SHEET 2'!U17 -> 5257.6619 | F29: =+E29*D29 -> 21030.647
A30: 16 | B30: 9000574302 | C30: INDEX 1聽 SUPPORT PLATE | D30: 4 | E30: =+'SHEET 2'!U18 -> 477.00094 | F30: =+E30*D30 -> 1908.0038
A31: 17 | B31: 9000650903 | C31: PREFORM SCALE SUPPORT PLATE | D31: 4 | E31: =+'SHEET 2'!U19 -> 7745.4688 | F31: =+E31*D31 -> 30981.875
A32: 18 | B32: 9000692404 | C32: TENSIONER BEARING SHAFT FOR BOTTLE | D32: 2 | E32: =+'SHEET 2'!U20 -> 641.73175 | F32: =+E32*D32 -> 1283.4635
A33: 19 | B33: 9000692703 | C33: TENSIONER BEARING SHAFT - 75H | D33: 6 | E33: =+'SHEET 2'!U21 -> 702.16469 | F33: =+E33*D33 -> 4212.9881
A34: 20 | B34: 9000700403 | C34: BOTTLE EJECTOR CYLINDER MTG. PLATE | D34: 1 | E34: =+'SHEET 2'!U22 -> 1162.2591 | F34: =+E34*D34 -> 1162.2591
A35: 21 | B35: 9000722603 | C35: SUPPORT BEARING MTG. PLATE | D35: 16 | E35: =+'SHEET 2'!U23 -> 2656.9336 | F35: =+E35*D35 -> 42510.938
A36: 22 | B36: 9000734304 | C36: CAM BASE PLATE MOUNTING BEAM | D36: 1 | E36: =+'SHEET 2'!U24 -> 16562.5 | F36: =+E36*D36 -> 16562.5
A37: 23 | B37: 9000736504 | C37: BRACKET FOR PHOTOCELL & REFLECTOR | D37: 1 | E37: =+'SHEET 2'!U25 -> 1249 | F37: =+E37*D37 -> 1249
... A46: 32 | B46: 9001301502 | C46: STOPPER NYLONE FOR SHUTTLE | D46: 2 | E46: =+'SHEET 2'!U34 -> 283.41 | F46: =+E46*D46 -> 566.82
A47: 33 | B47: 9001301702 | C47: MOUNTING LOWER PLATE FOR EXTRUSION MOUNT | D47: 4 | E47: =+'SHEET 2'!U35 -> 0 | F47: =+E47*D47 -> 0 | G47: DRAWING REQUIRED
A48: 34 | B48: 9001309502 | C48: PLATE FOR WEDGE CLAMP | D48: 64 | E48: =+'SHEET 2'!U36 -> 514.28 | F48: =+E48*D48 -> 32913.92
A49: 35 | B49: 9001312101 | C49: BASE PLATE FOR LOADER | D49: 7 | E49: =+'SHEET 2'!U37 -> 6072.56 | F49: =+E49*D49 -> 42507.92
A50: 36 | B50: 9001312202 | C50: BLOCK FOR SYF BEARING LOADER | D50: 7 | E50: =+'SHEET 2'!U38 -> 932.601 | F50: =+E50*D50 -> 6528.207
A51: 37 | B51: 9001312302 | C51: BLOCK FOR SYF BEARING GEAR SIDE | D51: 7 | E51: =+'SHEET 2'!U39 -> 1340.924 | F51: =+E51*D51 -> 9386.468
A52: 38 | B52: 9001312402 | C52: PLATE FOR LOADER MTG. | D52: 14 | E52: =+'SHEET 2'!U40 -> 1345.6201 | F52: =+E52*D52 -> 18838.681
A53: 39 | B53: 9001312501 | C53: BOLT FOR STOPER LONG 140MM | D53: 7 | E53: =+'SHEET 2'!U41 -> 468.34539 | F53: =+E53*D53 -> 3278.4177
A54: 40 | B54: 9001312603 | C54: BLOCK FOR COUNTER WIEGHT LOADER | D54: 7 | E54: =+'SHEET 2'!U42 -> 1184.0125 | F54: =+E54*D54 -> 8288.0875
A55: 41 | B55: 9001312702 | C55: SHIM FOR 1MM LOADER | D55: 60 | E55: =+'SHEET 2'!U43 -> 0 | F55: =+E55*D55 -> 0 | G55: DRAWING REQUIRED
A56: 42 | B56: 9001317602 | C56: SUPPORT TWISTER SPINDLE ROLLER GUIDE | D56: 2 | E56: =+'SHEET 2'!U44 -> 4000 | F56: =+E56*D56 -> 8000
A57: 43 | B57: 9001317702 | C57: BRACKET L FOR PREFORM PRESSING | D57: 2 | E57: =+'SHEET 2'!U45 -> 788.69008 | F57: =+E57*D57 -> 1577.3802
A58: 44 | B58: 9001690802 | C58: ASSEMBLY GATE UNIT MOUTING SUPPORT | D58: 1 | E58: =+'SHEET 2'!U46 -> 0 | F58: =+E58*D58 -> 0 | G58: ASSY DRAWING
A59: 45 | B59: 9001694802 | C59: PITCH 180MM VERTICAL PLATE | D59: 1 | E59: =+'SHEET 2'!U47 -> 3918.0902 | F59: =+E59*D59 -> 3918.0902
A60: 46 | B60: 9001721601 | C60: BLOCK FOR W MTG BKT 2 | D60: 1 | E60: =+'SHEET 2'!U48 -> 890.81367 | F60: =+E60*D60 -> 890.81367
A61: 47 | B61: 9001722001 | C61: BLOCK FOR W MTG BKT 1 | D61: 1 | E61: =+'SHEET 2'!U49 -> 1067.114 | F61: =+E61*D61 -> 1067.114
A62: 48 | B62: 9001781201 | C62: BLOW PIN 2 | D62: 16 | E62: =+'SHEET 2'!U50 -> 855 | F62: =+E62*D62 -> 13680
A63: 49 | B63: 9001783601 | C63: PLATE MESH FOR FESTO VENTURI BOX | D63: 1 | E63: =+'SHEET 2'!U51 -> 570.11562 | F63: =+E63*D63 -> 570.11562
A64: 50 | B64: 9001783701 | C64: SPACER FOR FESTO VENTURI BOX | D64: 2 | E64: =+'SHEET 2'!U52 -> 100 | F64: =+E64*D64 -> 200
A65: 51 | B65: 9001783801 | C65: BOX CASING FOR FESTO VENTURI | D65: 1 | E65: =+'SHEET 2'!U53 -> 20416.948 | F65: =+E65*D65 -> 20416.948
A66: 52 | B66: 9001783901 | C66: BOX CASING LID FOR FESTO VENTURI | D66: 1 | E66: =+'SHEET 2'!U54 -> 1302.7053 | F66: =+E66*D66 -> 1302.7053
A67: 53 | B67: 9001794101 | C67: COOLING WATER LINE L BKT | D67: 1 | E67: =+'SHEET 2'!U55 -> 564.11487 | F67: =+E67*D67 -> 564.11487
A68: 54 | B68: 9001795601 | C68: BRACKET LIMIT SWITCH | D68: 1 | E68: =+'SHEET 2'!U56 -> 394.42875 | F68: =+E68*D68 -> 394.42875
A69: 55 | B69: 9001797301 | C69: SUPPORT NON OVEN SIDE | D69: 2 | E69: =+'SHEET 2'!U57 -> 443.81016 | F69: =+E69*D69 -> 887.62031
A70: 56 | B70: 9001798901 | C70: VALVE MOUNTING PLATE MFH-1/4 | D70: 1 | E70: =+'SHEET 2'!U58 -> 534.64375 | F70: =+E70*D70 -> 534.64375
... A80: 66 | B80: 9001811001 | C80: ADAPTER FOR SMC ZHV-10 VENTURI | D80: 6 | E80: =+'SHEET 2'!U68 -> 274.3282 | F80: =+E80*D80 -> 1645.9692
A81: 67 | B81: 9001813201 | C81: SHAFT ASSEMBLY FOR DRVS | D81: 6 | E81: =+'SHEET 2'!U69 -> 0 | F81: =+E81*D81 -> 0 | G81: REGRATE
A82: 68 | B82: 9001816401 | C82: BLOCK HEATER MTG. BOTTOM | D82: 2 | E82: =+'SHEET 2'!U70 -> 1116.27 | F82: =+E82*D82 -> 2232.54
A83: 69 | B83: 9001816501 | C83: BLOCK HEATER MTG. BOTTOM CENTER | D83: 4 | E83: =+'SHEET 2'!U71 -> 1502.659 | F83: =+E83*D83 -> 6010.636
A84: 70 | B84: 9001816601 | C84: BRACKET | D84: 8 | E84: =+'SHEET 2'!U72 -> 174.93 | F84: =+E84*D84 -> 1399.44
A85: 71 | B85: 9001816701 | C85: BRACKET | D85: 8 | E85: =+'SHEET 2'!U73 -> 231.1275 | F85: =+E85*D85 -> 1849.02
A86: 72 | B86: 9001816901 | C86: BLOCK HEATER MTG. BOTTOM LEFT | D86: 2 | E86: =+'SHEET 2'!U74 -> 1116.27 | F86: =+E86*D86 -> 2232.54
A87: 73 | B87: 9001817201 | C87: CLAMPING BKT FOR SICA CABLE TRAY | D87: 24 | E87: =+'SHEET 2'!U75 -> 207.41825 | F87: =+E87*D87 -> 4978.038
A88: 74 | B88: 9001823901 | C88: QUARTZ BAR MOUNTING CLAMP | D88: 24 | E88: =+'SHEET 2'!U76 -> 165.19325 | F88: =+E88*D88 -> 3964.638
A89: 75 | B89: 9001827001 | C89: SHIM FOR STOPPER BLOCK 0.4 MM | D89: 88 | E89: =+'SHEET 2'!U77 -> 101.63858 | F89: =+E89*D89 -> 8944.1946
A90: 76 | B90: 9001827701 | C90: SHIM FOR STOPPER BLOCK 0.2 MM | D90: 36 | E90: =+'SHEET 2'!U78 -> 101.63858 | F90: =+E90*D90 -> 3658.9887
A91: 77 | B91: 9001832601 | C91: HOT NECK COLLER GUIDE | D91: 1 | E91: =+'SHEET 2'!U79 -> 6664.1287 | F91: =+E91*D91 -> 6664.1287
A92: 78 | B92: 9001835301 | C92: BOTTLE OUTFEED NECK GUIDE PLATE_V25 | D92: 1 | E92: =+'SHEET 2'!U80 -> 19629 | F92: =+E92*D92 -> 19629
A93: 79 | B93: 9001837501 | C93: PLATE FRONT COVER CENTRE FOR PILLAR | D93: 4 | E93: =+'SHEET 2'!U81 -> 1284.412 | F93: =+E93*D93 -> 5137.648
A94: 80 | B94: 9001842201 | C94: CLAMP FOR 6MM PIPE | D94: 18 | E94: =+'SHEET 2'!U82 -> 65.51625 | F94: =+E94*D94 -> 1179.2925
A95: 81 | B95: 9001844301 | C95: HOPPER CAP COLLECTING | D95: 3 | E95: =+'SHEET 2'!U83 -> 0 | F95: =+E95*D95 -> 0 | G95: REGRATE
A96: 82 | B96: 9001846901 | C96: TUBE OD 6MM, LG 5M | D96: 3 | E96: =+'SHEET 2'!U84 -> 1991.25 | F96: =+E96*D96 -> 5973.75
A97: 83 | B97: 9001852401 | C97: NECK GUIDE COLLAR SUPPORT | D97: 2 | E97: =+'SHEET 2'!U85 -> 1121.7 | F97: =+E97*D97 -> 2243.4
A98: 84 | B98: 9001852901 | C98: NECK GUIDE COLLAR SUPPORT-S.S | D98: 2 | E98: =+'SHEET 2'!U86 -> 2897.75 | F98: =+E98*D98 -> 5795.5
A99: 85 | B99: 9001853001 | C99: RING FOR HOT PREFORM TOP HOLDING-S.S | D99: 8 | E99: =+'SHEET 2'!U87 -> 4878 | F99: =+E99*D99 -> 39024
A100: 86 | B100: 9001853201 | C100: RESTING PAD FOR FLAT BOTTLES-SR 5/2N | D100: 1 | E100: =+'SHEET 2'!U88 -> 1683.4975 | F100: =+E100*D100 -> 1683.4975
A101: 87 | B101: 9001854801 | C101: ROD | D101: 2 | E101: =+'SHEET 2'!U89 -> 607.7615 | F101: =+E101*D101 -> 1215.523
A102: 88 | B102: 9001855001 | C102: PLATE FOR CYLINDER MTG SHUTTLE | D102: 6 | E102: =+'SHEET 2'!U90 -> 696.74297 | F102: =+E102*D102 -> 4180.4578
A103: 89 | B103: 9001855301 | C103: STOPPER NYLON SHUTTLE 27.5MM | D103: 6 | E103: =+'SHEET 2'!U91 -> 297.02005 | F103: =+E103*D103 -> 1782.1203
A104: 90 | B104: 9001856401 | C104: STOPPER SHUTTLE 19MM | D104: 6 | E104: =+'SHEET 2'!U92 -> 297.02005 | F104: =+E104*D104 -> 1782.1203
A105: 91 | B105: 9001856501 | C105: MOUNTING PLATE FOR W BRACKET GATE 1 | D105: 6 | E105: =+'SHEET 2'!U93 -> 920 | F105: =+E105*D105 -> 5520
A106: 92 | B106: 9001856601 | C106: MOUNTING PLATE FOR AUTO LUBRICATION | D106: 5 | E106: =+'SHEET 2'!U94 -> 1257.7969 | F106: =+E106*D106 -> 6288.9844
A107: 93 | B107: 9001856701 | C107: BASE PLATE FOR ELECTRICAL INDEXING | D107: 2 | E107: =+'SHEET 2'!U95 -> 7358 | F107: =+E107*D107 -> 14716
... A111: 97 | B111: 9001857901 | C111: PUSHER NYLON HOLDER | D111: 2 | E111: =+'SHEET 2'!U99 -> 476 | F111: =+E111*D111 -> 952
A112: 98 | B112: 9001859001 | C112: PIPE T JOIN FOR HYDRA | D112: 1 | E112: =+'SHEET 2'!U100 -> 0 | F112: =+E112*D112 -> 0 | G112: REGRATE
A113: 99 | B113: 9001861001 | C113: STRETCHING ROD GUIDE BUDH-SR_5/2 | D113: 2 | E113: =+'SHEET 2'!U101 -> 807.43903 | F113: =+E113*D113 -> 1614.8781
A114: 100 | B114: 9001861101 | C114: SEAL UNIT-3(12.7 STRETCH ROD)-5/2 | D114: 2 | E114: =+'SHEET 2'!U102 -> 850.26628 | F114: =+E114*D114 -> 1700.5326
A115: 101 | B115: 9001861201 | C115: SEAL UNIT-2(12.7 STRETCH ROD)-5/2 | D115: 2 | E115: =+'SHEET 2'!U103 -> 1047.2079 | F115: =+E115*D115 -> 2094.4157
A116: 102 | B116: 9001861401 | C116: CYLINDRICAL BUSH (20X25)-SR 5/2 | D116: 2 | E116: =+'SHEET 2'!U104 -> 285.1957 | F116: =+E116*D116 -> 570.39141
A117: 103 | B117: 9001861501 | C117: BUSH (SPIDER)_12.7_SR 5/2 | D117: 2 | E117: =+'SHEET 2'!U105 -> 846.65681 | F117: =+E117*D117 -> 1693.3136
D118: Total | F118: =SUM(F15:F117) -> 765381.77
A119: Terms & Conditions
A120: Prices quoted are for Ex-Works
A121: Packing & Forwarding Charges Will be extra
...

Sheet SHEET 2
A2: Sr No | B2: Drawing No. | C2: Description | D2: Material | E2: Material Size | H2: Wight | I2: Material Cost | J2: CNC / Turning | K2: Milling/Cutting | L2: VMC | M2: Drilling | N2: Taping | O2: Grinding | P2: Laser Cutting & Bending | Q2: Sparking/HRC/WELD | R2: Finish | S2: Profit &over heads | T2: Qty | U2: Unit price | V2: Total Price | X2: REMARK
A3: 1 | B3: 9000011003 | C3: COOLING RAIL SUPPORT PLATE ( | D3: Alu 6060 | E3: 12 | F3: 32 | G3: 40 | H3: =+E3*F3*G3*2.77/1000000 -> 0.0425472 | I3: =H3*450 -> 19.14624 | J3: 0 | K3: 120 | L3: 0 | M3: 50 | N3: 0 | O3: 0 | P3: 0 | Q3: 0 | R3: 0 | S3: =SUM(I3:R3)*25% -> 47.28656 | T3: 16 | U3: =+SUM(I3:S3) -> 236.4328 | V3: =U3*T3 -> 3782.9248
A4: 2 | B4: 9000011103 | C4: COOLING RAIL SUPPORT PLATE ( | D4: Alu 6060 | E4: 12 | F4: 32 | G4: 60 | H4: =+E4*F4*G4*2.77/1000000 -> 0.0638208 | I4: =H4*450 -> 28.71936 | J4: 0 | K4: 120 | L4: 0 | M4: 50 | N4: 0 | O4: 0 | P4: 0 | Q4: 0 | R4: 0 | S4: =SUM(I4:R4)*25% -> 49.67984 | T4: 8 | U4: =+SUM(I4:S4) -> 248.3992 | V4: =U4*T4 -> 1987.1936
A5: 3 | B5: 9000118001 | C5: SPACER FOR AIR COLLECTOR 40 RUBIN (0425@ | D5: SS316L | E5: 25 | G5: 30 | H5: =+E5*E5*3.14/4*G5*8.55/1000000 -> 0.12584531 | I5: =H5*350 -> 44.045859 | J5: 220 | K5: 0 | L5: 0 | M5: 50 | N5: 0 | O5: 0 | P5: 0 | Q5: 0 | R5: 0 | S5: =SUM(I5:R5)*25% -> 78.511465 | T5: 8 | U5: =+SUM(I5:S5) -> 392.55732 | V5: =U5*T5 -> 3140.4586
A6: 4 | B6: 9000152202 | C6: 1/2N CLAMP UNIT PINION HOLDING BLOCK | D6: MS | E6: 160 | F6: 120 | G6: 55 | H6: =+E6*F6*G6*7.85/1000000 -> 8.2896 | I6: =H6*90 -> 746.064 | J6: 0 | K6: 300 | L6: 1600 | M6: 100 | N6: 100 | O6: 100 | P6: 0 | Q6: 0 | R6: =+H6*25 -> 207.24 | S6: =SUM(I6:R6)*20% -> 630.6608 | T6: 1 | U6: =+SUM(I6:S6) -> 3783.9648 | V6: =U6*T6 -> 3783.9648
A7: 5 | B7: 9000166101 | C7: CENTER HEATER STAND COVER TOP SIDE | D7: ALU | E7: 65 | F7: 65 | G7: 16 | H7: =+E7*F7*G7*2.77/1000000 -> 0.187252 | I7: =H7*450 -> 84.2634 | J7: 0 | K7: 120 | L7: 400 | M7: 0 | N7: 80 | O7: 0 | P7: 0 | Q7: 0 | R7: =+H7*250 -> 46.813 | S7: =SUM(I7:R7)*25% -> 182.7691 | T7: 1 | U7: =+SUM(I7:S7) -> 913.8455 | V7: =U7*T7 -> 913.8455
A8: 6 | B8: 9000182703 | C8: SPRING FOR CLAMP UNIT FOR 1/4N | D8: STD | E8: 0 | F8: 0 | G8: 0 | H8: =+E8*F8*G8*7.85/1000000 -> 0 | I8: =H8*100 -> 0 | J8: 600 | K8: 0 | L8: 0 | M8: 0 | N8: 0 | O8: 0 | P8: 0 | Q8: 0 | R8: =H8*25 -> 0 | S8: =SUM(I8:R8)*25% -> 150 | T8: 16 | U8: =+SUM(I8:S8) -> 750 | V8: =U8*T8 -> 12000
A9: 7 | B9: 9000184102 | C9: CYLINDER EXTENSION FOR SLIDING PLATE | D9: MS | E9: 32 | G9: 265 | H9: =+E9*E9*3.14/4*G9*7.85/1000000 -> 1.6721882 | I9: =H9*90 -> 150.49693 | J9: 450 | K9: 80 | L9: 0 | M9: 0 | N9: 20 | O9: 0 | P9: 0 | Q9: 0 | R9: =+H9*25 -> 41.804704 | S9: =SUM(I9:R9)*25% -> 185.57541 | T9: 8 | U9: =+SUM(I9:S9) -> 927.87705 | V9: =U9*T9 -> 7423.0164
A10: 8 | B10: 9000197803 | C10: TIE BAR LOCKING | D10: Alu 6060 | E10: 55 | F10: 55 | G10: 605 | H10: =+E10*F10*G10*2.77/1000000 -> 5.0694463 | I10: =+H10*450 -> 2281.2508 | J10: 0 | K10: 600 | L10: 0 | M10: =16*25 -> 400 | N10: =6*20 -> 120 | O10: 0 | P10: 0 | Q10: 0 | R10: 0 | S10: =SUM(I10:R10)*25% -> 850.3127 | T10: 8 | U10: =+SUM(I10:S10) -> 4251.5635 | V10: =U10*T10 -> 34012.508
A11: 9 | B11: 9000229001 | C11: EJECTOR JAW HOLDING PLATE | D11: MS | E11: 40 | F11: 20 | G11: 5 | H11: =+E11*F11*G11*7.85/1000000 -> 0.0314 | I11: =H11*90 -> 2.826 | J11: 0 | K11: 0 | L11: 0 | M11: 0 | N11: 0 | O11: 0 | P11: 80 | Q11: 0 | R11: =+H11*20 -> 0.628 | S11: =SUM(I11:R11)*25% -> 20.8635 | T11: 24 | U11: =+SUM(I11:S11) -> 104.3175 | V11: =U11*T11 -> 2503.62
A12: 10 | B12: 9000234902 | C12: SPACER FOR NORGREN VALVE MTG.BRACKET | D12: MS | E12: 50 | F12: 25 | G12: 25 | H12: =+E12*F12*G12*7.85/1000000 -> 0.2453125 | I12: =H12*90 -> 22.078125 | J12: 0 | K12: 80 | L12: 0 | M12: 40 | N12: 40 | O12: 0 | P12: 0 | Q12: 0 | R12: =H12*25 -> 6.1328125 | S12: =SUM(I12:R12)*25% -> 47.052734 | T12: 4 | U12: =+SUM(I12:S12) -> 235.26367 | V12: =U12*T12 -> 941.05469
A13: 11 | B13: 9000236502 | C13: BLOW PIN BUSH SR 1/2 | D13: UB | E13: 0 | G13: 0 | H13: =+E13*E13*3.14/4*G13*7.85/1000000 -> 0 | I13: =H13*100 -> 0 | J13: 0 | K13: 0 | L13: 0 | M13: 0 | N13: 0 | O13: 0 | P13: 0 | Q13: 0 | R13: 0 | S13: =SUM(I13:R13)*25% -> 0 | T13: 4 | U13: =+SUM(I13:S13) -> 0 | V13: =U13*T13 -> 0 | W13: UB MATERIAL NOT CLEAR
A14: 12 | B14: 9000392401 | C14: BOLT FOR LOADER TIE BAR | D14: EN8 | E14: 20 | G14: 55 | H14: =+E14*E14*3.14/4*G14*7.85/1000000 -> 0.1355695 | I14: =H14*100 -> 13.55695 | J14: 120 | K14: 0 | L14: 0 | M14: 0 | N14: 0 | O14: 0 | P14: 0 | Q14: 10 | R14: =H14*25 -> 3.3892375 | S14: =SUM(I14:R14)*25% -> 36.736547 | T14: 14 | U14: =+SUM(I14:S14) -> 183.68273 | V14: =U14*T14 -> 2571.5583
A15: 13 | B15: 9000392901 | C15: LOADER GRIPPER HOLDING PLATE FOR 1-4GRE@ | D15: ALU | E15: 445 | F15: 225 | G15: 20 | H15: =+E15*F15*G15*2.55/1000000 -> 5.106375 | I15: =+H15*450 -> 2297.8688 | J15: 0 | K15: 750 | L15: 1200 | M15: =6*20 -> 120 | N15: 120 | O15: 0 | P15: 0 | Q15: 0 | R15: =+H15*350 -> 1787.2313 | S15: =SUM(I15:R15)*25% -> 1568.775 | T15: 7 | U15: =+SUM(I15:S15) -> 7843.875 | V15: =U15*T15 -> 54907.125
A16: 14 | B16: 9000513803 | C16: BLOW PIN BUSH | D16: PET | E16: 90 | G16: 90 | H16: =+E16*E16*3.14/4*G16*1.77/1000000 -> 1.012909 | I16: =H16*2000 -> 2025.8181 | J16: 450 | K16: 0 | L16: 0 | M16: 0 | N16: 0 | O16: 0 | P16: 0 | Q16: 0 | R16: 0 | S16: =SUM(I16:R16)*25% -> 618.95452 | T16: 8 | U16: =+SUM(I16:S16) -> 3094.7726 | V16: =U16*T16 -> 24758.181
A17: 15 | B17: 9000569303 | C17: TIE-BAR LOCKING PLATE | D17: MS | E17: 760 | F17: 65 | G17: 55 | H17: =+E17*F17*G17*7.85/1000000 -> 21.32845 | I17: =H17*90 -> 1919.5605 | J17: 0 | K17: 1200 | L17: 0 | M17: =20*25 -> 500 | N17: =8*20 -> 160 | O17: 0 | P17: 0 | Q17: 0 | R17: =+H17*20 -> 426.569 | S17: =SUM(I17:R17)*25% -> 1051.5324 | T17: 4 | U17: =+SUM(I17:S17) -> 5257.6619 | V17: =U17*T17 -> 21030.647
A18: 16 | B18: 9000574302 | C18: INDEX 1聽 SUPPORT PLATE | D18: MS | E18: 105 | F18: 30 | G18: 30 | H18: =+E18*F18*G18*7.85/1000000 -> 0.741825 | I18: =H18*90 -> 66.76425 | J18: 0 | K18: 160 | L18: 0 | M18: 100 | N18: 40 | O18: 0 | P18: 0 | Q18: 0 | R18: =+H18*20 -> 14.8365 | S18: =SUM(I18:R18)*25% -> 95.400188 | T18: 4 | U18: =+SUM(I18:S18) -> 477.00094 | V18: =U18*T18 -> 1908.0038
A19: 17 | B19: 9000650903 | C19: PREFORM SCALE SUPPORT PLATE | D19: MS | E19: 3500 | F19: 50 | G19: 10 | H19: =+E19*F19*G19*7.85/1000000 -> 13.7375 | I19: =+H19*90 -> 1236.375 | J19: 0 | K19: 0 | L19: =8*400 -> 3200 | M19: =8*20 -> 160 | N19: =40*20 -> 800 | O19: 0 | P19: 0 | Q19: 0 | R19: 800 | S19: =SUM(I19:R19)*25% -> 1549.0938 | T19: 4 | U19: =+SUM(I19:S19) -> 7745.4688 | V19: =U19*T19 -> 30981.875
A20: 18 | B20: 9000692404 | C20: TENSIONER BEARING SHAFT FOR BOTTLE | D20: MS | E20: 40 | G20: 100 | H20: =+E20*E20*3.14/4*G20*7.85/1000000 -> 0.98596 | I20: =+H20*90 -> 88.7364 | J20: 180 | K20: 80 | L20: 0 | M20: 0 | N20: 20 | O20: 120 | P20: 0 | Q20: 0 | R20: =+H20*25 -> 24.649 | S20: =SUM(I20:R20)*25% -> 128.34635 | T20: 2 | U20: =+SUM(I20:S20) -> 641.73175 | V20: =U20*T20 -> 1283.4635
A21: 19 | B21: 9000692703 | C21: TENSIONER BEARING SHAFT - 75H | D21: MS | E21: 40 | G21: 125 | H21: =+E21*E21*3.14/4*G21*7.85/1000000 -> 1.23245 | I21: =+H21*90 -> 110.9205 | J21: 200 | K21: 80 | L21: 0 | M21: 0 | N21: 20 | O21: 120 | P21: 0 | Q21: 0 | R21: =+H21*25 -> 30.81125 | S21: =SUM(I21:R21)*25% -> 140.43294 | T21: 6 | U21: =+SUM(I21:S21) -> 702.16469 | V21: =U21*T21 -> 4212.9881
A22: 20 | B22: 9000700403 | C22: BOTTLE EJECTOR CYLINDER MTG. PLATE | D22: MS | E22: 165 | F22: 95 | G22: 12 | H22: =+E22*F22*G22*7.85/1000000 -> 1.476585 | I22: =H22*90 -> 132.89265 | J22: 0 | K22: 160 | L22: 400 | M22: 0 | N22: =4*20 -> 80 | O22: 120 | P22: 0 | Q22: 0 | R22: =+H22*25 -> 36.914625 | S22: =SUM(I22:R22)*25% -> 232.45182 | T22: 1 | U22: =+SUM(I22:S22) -> 1162.2591 | V22: =U22*T22 -> 1162.2591
A23: 21 | B23: 9000722603 | C23: SUPPORT BEARING MTG. PLATE | D23: C45 | E23: 85 | F23: 125 | G23: 60 | H23: =+E23*F23*G23*7.85/1000000 -> 5.004375 | I23: =H23*100 -> 500.4375 | J23: 0 | K23: 220 | L23: 1200 | M23: 0 | N23: 80 | O23: 0 | P23: 0 | Q23: 0 | R23: =+H23*25 -> 125.10937 | S23: =SUM(I23:R23)*25% -> 531.38672 | T23: 16 | U23: =+SUM(I23:S23) -> 2656.9336 | V23: =U23*T23 -> 42510.938
A24: 22 | B24: 9000734304 | C24: CAM BASE PLATE MOUNTING BEAM | D24: MS | E24: 0 | F24: 0 | G24: 0 | H24: 43 | I24: 3855 | J24: 800 | K24: 1600 | L24: 3200 | M24: 0 | N24: =7*20 -> 140 | O24: 0 | P24: 0 | Q24: =43*60 -> 2580 | R24: =43*25 -> 1075 | S24: =SUM(I24:R24)*25% -> 3312.5 | T24: 1 | U24: =+SUM(I24:S24) -> 16562.5 | V24: =U24*T24 -> 16562.5
A25: 23 | B25: 9000736504 | C25: BRACKET FOR PHOTOCELL & REFLECTOR | D25: MS | E25: 700 | F25: 100 | G25: 10 | H25: =+E25*F25*G25*7.85/1000000 -> 5.495 | I25: =H25*90 -> 494.55 | J25: 0 | K25: 0 | L25: 0 | M25: 0 | N25: 40 | O25: 0 | P25: 800 | Q25: 0 | R25: =+H25*25 -> 137.375 | S25: =SUM(I25:R25)*25% -> 367.98125 | T25: 1 | U25: 1249 | V25: =U25*T25 -> 1249
A26: 24 | B26: 9000745006 | C26: C CHANNEL 1 | E26: 0 | F26: 0 | G26: 0 | H26: =+E26*F26*G26*7.85/1000000 -> 0 | I26: =H26*200 -> 0 | J26: 0 | K26: 0 | L26: 0 | M26: 0 | N26: 0 | O26: 0 | P26: 0 | Q26: 0 | R26: 200 | S26: =SUM(I26:R26)*25% -> 50 | T26: 2 | U26: =+SUM(I26:S26) -> 250 | V26: =U26*T26 -> 500
A27: 25 | B27: 9000745203 | C27: U - BRACKET FOR SPINDLE GUIDE SYSTEM | D27: MS | E27: 600 | F27: 150 | G27: 14 | H27: =+E27*F27*G27*7.85/1000000 -> 9.891 | I27: =+H27*90 -> 890.19 | J27: 0 | K27: 1200 | L27: 2400 | M27: 0 | N27: 120 | O27: 1200 | P27: 0 | Q27: 400 | R27: =+H27*25 -> 247.275 | S27: =SUM(I27:R27)*25% -> 1614.3663 | T27: 10 | U27: =+SUM(I27:S27) -> 8071.8313 | V27: =U27*T27 -> 80718.312
A28: 26 | B28: 9000746303 | C28: SPINDLE ROLLER GUIDE SUPPORT FOR IDLER @ | E28: 0 | F28: 0 | G28: 0 | H28: =+E28*F28*G28*7.85/1000000 -> 0 | I28: =H28*Z27 -> 0 | J28: 0 | K28: 0 | L28: 0 | M28: 0 | N28: 0 | O28: 0 | P28: 0 | Q28: 0 | R28: 0 | S28: =SUM(I28:R28)*25% -> 0 | T28: 1 | U28: 4000 | V28: =U28*T28 -> 4000 | X28: OLD RATE
A29: 27 | B29: 9000780902 | C29: GUIDE ROD | D29: EN24 | E29: 40 | G29: 165 | H29: =+E29*E29*3.14/4*G29*7.85/1000000 -> 1.626834 | I29: =+H29*120 -> 195.22008 | J29: 550 | K29: 80 | L29: 0 | M29: 0 | N29: 0 | O29: 0 | P29: 0 | Q29: 0 | R29: =+H29*25 -> 40.67085 | S29: =SUM(I29:R29)*25% -> 216.47273 | T29: 5 | U29: =+SUM(I29:S29) -> 1082.3637 | V29: =U29*T29 -> 5411.8183
A30: 28 | B30: 9001245102 | C30: SENSOR BASE MOUTING PLATE | D30: SS304 | E30: 450 | F30: 100 | G30: 6 | H30: =+E30*F30*G30*8.55/1000000 -> 2.3085 | I30: =+H30*320 -> 738.72 | J30: 0 | K30: 0 | L30: 0 | M30: 0 | N30: 0 | O30: 0 | P30: 250 | Q30: 0 | R30: 100 | S30: =SUM(I30:R30)*25% -> 272.18 | T30: 3 | U30: =+SUM(I30:S30) -> 1360.9 | V30: =U30*T30 -> 4082.7
A31: 29 | B31: 9001284403 | C31: BRACKET FOR SPINDLE GUIDE SYSTEM | D31: MS | E31: 450 | F31: 105 | G31: 25 | H31: =+E31*F31*G31*7.85/1000000 -> 9.2728125 | I31: =+H31*90 -> 834.55313 | J31: 0 | K31: 800 | L31: 1200 | M31: 0 | N31: 0 | O31: 1200 | P31: 0 | Q31: 350 | R31: =+H31*25 -> 231.82031 | S31: =SUM(I31:R31)*25% -> 1154.0934 | T31: 4 | U31: =+SUM(I31:S31) -> 5770.4668 | V31: =U31*T31 -> 23081.867
A32: 30 | B32: 9001293301 | C32: STUD FOR ADJUSTABLE TAKEOFF SUPPORT | D32: MS | E32: 14 | G32: 210 | H32: =+E32*E32*3.14/4*G32*7.85/1000000 -> 0.25363821 | I32: =H32*100 -> 25.363821 | J32: 160 | K32: 0 | L32: 80 | M32: 0 | N32: 0 | O32: 0 | P32: 0 | Q32: 0 | R32: 20 | S32: =SUM(I32:R32)*25% -> 71.340955 | T32: 8 | U32: =+SUM(I32:S32) -> 356.70478 | V32: =U32*T32 -> 2853.6382 | X32: OLD RATE
A33: 31 | B33: 9001300304 | C33: PLATE FOR VERTICAL 90MM PITCH | D33: MS | E33: 375 | F33: 200 | G33: 16 | H33: =+E33*F33*G33*7.85/1000000 -> 9.42 | I33: =H33*90 -> 847.8 | J33: 0 | K33: 650 | L33: 1200 | M33: 50 | N33: =8*20 -> 160 | O33: 0 | P33: 0 | Q33: 0 | R33: =+H33*25 -> 235.5 | S33: =SUM(I33:R33)*25% -> 785.825 | T33: 1 | U33: =+SUM(I33:S33) -> 3929.125 | V33: =U33*T33 -> 3929.125
A34: 32 | B34: 9001301502 | C34: STOPPER NYLONE FOR SHUTTLE | D34: POLYAMIDE | E34: 55 | F34: 30 | G34: 20 | H34: =+E34*F34*G34*1.77/1000000 -> 0.05841 | I34: =H34*800 -> 46.728 | J34: 0 | K34: 100 | L34: 0 | M34: 80 | N34: 0 | O34: 0 | P34: 0 | Q34: 0 | R34: 0 | S34: =SUM(I34:R34)*25% -> 56.682 | T34: 2 | U34: =+SUM(I34:S34) -> 283.41 | V34: =U34*T34 -> 566.82
A35: 33 | B35: 9001301702 | C35: MOUNTING LOWER PLATE FOR EXTRUSION MOUNT | E35: 0 | F35: 0 | G35: 0 | H35: =+E35*F35*G35*7.85/1000000 -> 0 | I35: =H35*200 -> 0 | J35: 0 | K35: 0 | L35: 0 | M35: 0 | N35: 0 | O35: 0 | P35: 0 | Q35: 0 | R35: 0 | S35: =SUM(I35:R35)*25% -> 0 | T35: 4 | U35: =+SUM(I35:S35) -> 0 | V35: =U35*T35 -> 0 | W35: DRAWING REQUIRED
A36: 34 | B36: 9001309502 | C36: PLATE FOR WEDGE CLAMP | D36: 100CR6 | E36: 80 | F36: 20 | G36: 20 | H36: =+E36*F36*G36*7.85/1000000 -> 0.2512 | I36: =H36*120 -> 30.144 | J36: 0 | K36: 200 | L36: 0 | M36: =6*25 -> 150 | N36: 0 | O36: 0 | P36: 0 | Q36: 25 | R36: =+H36*25 -> 6.28 | S36: =SUM(I36:R36)*25% -> 102.856 | T36: 64 | U36: =+SUM(I36:S36) -> 514.28 | V36: =U36*T36 -> 32913.92
A37: 35 | B37: 9001312101 | C37: BASE PLATE FOR LOADER | D37: MS | E37: 555 | F37: 165 | G37: 18 | H37: =+E37*F37*G37*7.85/1000000 -> 12.939547 | I37: =H37*90 -> 1164.5593 | J37: 0 | K37: 650 | L37: =6*400 -> 2400 | M37: 0 | N37: =16*20 -> 320 | O37: 0 | P37: 0 | Q37: 0 | R37: =+H37*25 -> 323.48869 | S37: =SUM(I37:R37)*25% -> 1214.512 | T37: 7 | U37: =+SUM(I37:S37) -> 6072.56 | V37: =U37*T37 -> 42507.92
A38: 36 | B38: 9001312202 | C38: BLOCK FOR SYF BEARING LOADER | D38: ALU 7075 | E38: 122 | F38: 40 | G38: 55 | H38: =+E38*F38*G38*2.77/1000000 -> 0.743468 | I38: =H38*450 -> 334.5606 | J38: 0 | K38: 150 | L38: 0 | M38: =6*25 -> 150 | N38: 0 | O38: 0 | P38: 0 | Q38: 0 | R38: =+H38*150 -> 111.5202 | S38: =SUM(I38:R38)*25% -> 186.5202 | T38: 7 | U38: =+SUM(I38:S38) -> 932.601 | V38: =U38*T38 -> 6528.207
A39: 37 | B39: 9001312302 | C39: BLOCK FOR SYF BEARING GEAR SIDE | D39: ALU 7075 | E39: 122 | F39: 70 | G39: 40 | H39: =+E39*F39*G39*2.77/1000000 -> 0.946232 | I39: =H39*450 -> 425.8044 | J39: 0 | K39: 220 | L39: 0 | M39: =9*25 -> 225 | N39: 60 | O39: 0 | P39: 0 | Q39: 0 | R39: =+H39*150 -> 141.9348 | S39: =SUM(I39:R39)*25% -> 268.1848 | T39: 7 | U39: =+SUM(I39:S39) -> 1340.924 | V39: =U39*T39 -> 9386.468
A40: 38 | B40: 9001312402 | C40: PLATE FOR LOADER MTG. | D40: MS | E40: 265 | F40: 78 | G40: 25 | H40: =+E40*F40*G40*7.85/1000000 -> 4.0564875 | I40: =H40*90 -> 365.08388 | J40: 0 | K40: 350 | L40: 200 | M40: 0 | N40: 60 | O40: 0 | P40: 0 | Q40: 0 | R40: =+H40*25 -> 101.41219 | S40: =SUM(I40:R40)*25% -> 269.12402 | T40: 14 | U40: =+SUM(I40:S40) -> 1345.6201 | V40: =U40*T40 -> 18838.681
A41: 39 | B41: 9001312501 | C41: BOLT FOR STOPER LONG 140MM | D41: MS | E41: 20 | G41: 145 | H41: =+E41*E41*3.14/4*G41*7.85/1000000 -> 0.3574105 | I41: =H41*100 -> 35.74105 | J41: 250 | K41: 80 | L41: 0 | M41: 0 | N41: 0 | O41: 0 | P41: 0 | Q41: 0 | R41: =+H41*25 -> 8.9352625 | S41: =SUM(I41:R41)*25% -> 93.669078 | T41: 7 | U41: =+SUM(I41:S41) -> 468.34539 | V41: =U41*T41 -> 3278.4177
A42: 40 | B42: 9001312603 | C42: BLOCK FOR COUNTER WIEGHT LOADER | D42: MS | E42: 275 | F42: 40 | G42: 40 | H42: =+E42*F42*G42*7.85/1000000 -> 3.454 | I42: =H42*90 -> 310.86 | J42: 0 | K42: 450 | L42: 0 | M42: =4*25 -> 100 | N42: 0 | O42: 0 | P42: 0 | Q42: 0 | R42: =+H42*25 -> 86.35 | S42: =SUM(I42:R42)*25% -> 236.8025 | T42: 7 | U42: =+SUM(I42:S42) -> 1184.0125 | V42: =U42*T42 -> 8288.0875
A43: 41 | B43: 9001312702 | C43: SHIM FOR 1MM LOADER | E43: 0 | F43: 0 | G43: 0 | H43: =+E43*F43*G43*7.85/1000000 -> 0 | I43: =H43*Z42 -> 0 | J43: 0 | K43: 0 | L43: 0 | M43: 0 | N43: 0 | O43: 0 | P43: 0 | Q43: 0 | R43: 0 | S43: =SUM(I43:R43)*25% -> 0 | T43: 60 | U43: =+SUM(I43:S43) -> 0 | V43: =U43*T43 -> 0 | W43: DRAWING REQUIRED
A44: 42 | B44: 9001317602 | C44: SUPPORT TWISTER SPINDLE ROLLER GUIDE | D44: MS | E44: 0 | F44: 0 | G44: 0 | H44: =+E44*F44*G44*7.85/1000000 -> 0 | I44: =H44*Z43 -> 0 | J44: 0 | K44: 0 | L44: 0 | M44: 0 | N44: 0 | O44: 0 | P44: 0 | Q44: 0 | R44: 0 | S44: =SUM(I44:R44)*25% -> 0 | T44: 2 | U44: 4000 | V44: =U44*T44 -> 8000 | X44: OLD RATE
A45: 43 | B45: 9001317702 | C45: BRACKET L FOR PREFORM PRESSING | D45: MS | E45: =110+45 -> 155 | F45: 65 | G45: 10 | H45: =+E45*F45*G45*7.85/1000000 -> 0.7908875 | I45: =H45*90 -> 71.179875 | J45: 0 | K45: 220 | L45: 200 | M45: 0 | N45: 0 | O45: 0 | P45: 0 | Q45: 120 | R45: =+H45*25 -> 19.772187 | S45: =SUM(I45:R45)*25% -> 157.73802 | T45: 2 | U45: =+SUM(I45:S45) -> 788.69008 | V45: =U45*T45 -> 1577.3802
A46: 44 | B46: 9001690802 | C46: ASSEMBLY GATE UNIT MOUTING SUPPORT | E46: 0 | F46: 0 | G46: 0 | H46: =+E46*F46*G46*7.85/1000000 -> 0 | I46: =H46*Z45 -> 0 | J46: 0 | K46: 0 | L46: 0 | M46: 0 | N46: 0 | O46: 0 | P46: 0 | Q46: 0 | R46: 0 | S46: =SUM(I46:R46)*25% -> 0 | T46: 1 | U46: =+SUM(I46:S46) -> 0 | V46: =U46*T46 -> 0 | W46: ASSY DRAWING
A47: 45 | B47: 9001694802 | C47: PITCH 180MM VERTICAL PLATE | D47: MS | E47: 287 | F47: 207 | G47: 15 | H47: =+E47*F47*G47*7.85/1000000 -> 6.9954098 | I47: =H47*90 -> 629.58688 | J47: 0 | K47: 450 | L47: 1200 | M47: =6*25 -> 150 | N47: =10*25 -> 250 | O47: =28*20*0.5 -> 280 | P47: 0 | Q47: 0 | R47: =+H47*25 -> 174.88524 | S47: =SUM(I47:R47)*25% -> 783.61803 | T47: 1 | U47: =+SUM(I47:S47) -> 3918.0902 | V47: =U47*T47 -> 3918.0902
A48: 46 | B48: 9001721601 | C48: BLOCK FOR W MTG BKT 2 | D48: MS | E48: 75 | F48: 85 | G48: 30 | H48: =+E48*F48*G48*7.85/1000000 -> 1.5013125 | I48: =H48*90 -> 135.11812 | J48: 0 | K48: 250 | L48: 0 | M48: =10*25 -> 250 | N48: 40 | O48: 0 | P48: 0 | Q48: 0 | R48: =+H48*25 -> 37.532812 | S48: =SUM(I48:R48)*25% -> 178.16273 | T48: 1 | U48: =+SUM(I48:S48) -> 890.81367 | V48: =U48*T48 -> 890.81367
A49: 47 | B49: 9001722001 | C49: BLOCK FOR W MTG BKT 1 | D49: MS | E49: 95 | F49: 85 | G49: 30 | H49: =+E49*F49*G49*7.85/1000000 -> 1.9016625 | I49: =H49*90 -> 171.14963 | J49: 0 | K49: 300 | L49: 0 | M49: =11*25 -> 275 | N49: 60 | O49: 0 | P49: 0 | Q49: 0 | R49: =+H49*25 -> 47.541562 | S49: =SUM(I49:R49)*25% -> 213.4228 | T49: 1 | U49: =+SUM(I49:S49) -> 1067.114 | V49: =U49*T49 -> 1067.114
A50: 48 | B50: 9001781201 | C50: BLOW PIN 2 | E50: 0 | F50: 0 | G50: 0 | H50: =+E50*F50*G50*7.85/1000000 -> 0 | I50: =H50*Z49 -> 0 | J50: 0 | K50: 0 | L50: 0 | M50: 0 | N50: 0 | O50: 0 | P50: 0 | Q50: 0 | R50: 0 | S50: =SUM(I50:R50)*25% -> 0 | T50: 16 | U50: 855 | V50: =U50*T50 -> 13680 | X50: OLD RATE
A51: 49 | B51: 9001783601 | C51: PLATE MESH FOR FESTO VENTURI BOX | D51: ALU 6082 | E51: 150 | F51: 150 | G51: 2 | H51: =+E51*F51*G51*2.77/1000000 -> 0.12465 | I51: =H51*450 -> 56.0925 | J51: 0 | K51: 0 | L51: 0 | M51: 0 | N51: 0 | O51: 0 | P51: 400 | Q51: 0 | R51: 0 | S51: =SUM(I51:R51)*25% -> 114.02312 | T51: 1 | U51: =+SUM(I51:S51) -> 570.11562 | V51: =U51*T51 -> 570.11562
A52: 50 | B52: 9001783701 | C52: SPACER FOR FESTO VENTURI BOX | D52: ALU 6082 | E52: 8 | F52: 8 | G52: 115 | H52: =+E52*F52*G52*2.77/1000000 -> 0.0203872 | I52: =H52*450 -> 9.17424 | J52: 0 | K52: 80 | L52: 0 | M52: 0 | N52: 0 | O52: 0 | P52: 0 | Q52: 0 | R52: 0 | S52: =SUM(I52:R52)*25% -> 22.29356 | T52: 2 | U52: 100 | V52: =U52*T52 -> 200
A53: 51 | B53: 9001783801 | C53: BOX CASING FOR FESTO VENTURI | D53: ALU 6082 | E53: 305 | F53: 130 | G53: 150 | H53: =+E53*F53*G53*2.77/1000000 -> 16.474575 | I53: =H53*450 -> 7413.5588 | J53: 0 | K53: 1600 | L53: =18*400 -> 7200 | M53: 0 | N53: =6*20 -> 120 | O53: 0 | P53: 0 | Q53: 0 | R53: 0 | S53: =SUM(I53:R53)*25% -> 4083.3897 | T53: 1 | U53: =+SUM(I53:S53) -> 20416.948 | V53: =U53*T53 -> 20416.948
A54: 52 | B54: 9001783901 | C54: BOX CASING LID FOR FESTO VENTURI | D54: ALU 6082 | E54: 305 | F54: 150 | G54: 6 | H54: =+E54*F54*G54*2.77/1000000 -> 0.760365 | I54: =H54*450 -> 342.16425 | J54: 0 | K54: 350 | L54: 0 | M54: =14*25 -> 350 | N54: 0 | O54: 0 | P54: 0 | Q54: 0 | R54: 0 | S54: =SUM(I54:R54)*25% -> 260.54106 | T54: 1 | U54: =+SUM(I54:S54) -> 1302.7053 | V54: =U54*T54 -> 1302.7053
A55: 53 | B55: 9001794101 | C55: COOLING WATER LINE L BKT | D55: MS | E55: =210+120 -> 330 | F55: 30 | G55: 6 | H55: =+E55*F55*G55*7.85/1000000 -> 0.46629 | I55: =H55*90 -> 41.9661 | J55: 0 | K55: 0 | L55: 0 | M55: 0 | N55: 0 | O55: 0 | P55: 400 | Q55: 0 | R55: =+H55*20 -> 9.3258 | S55: =SUM(I55:R55)*25% -> 112.82297 | T55: 1 | U55: =+SUM(I55:S55) -> 564.11487 | V55: =U55*T55 -> 564.11487
A56: 54 | B56: 9001795601 | C56: BRACKET LIMIT SWITCH | D56: MS | E56: 120 | F56: 50 | G56: 3 | H56: =+E56*F56*G56*7.85/1000000 -> 0.1413 | I56: =H56*90 -> 12.717 | J56: 0 | K56: 0 | L56: 0 | M56: 0 | N56: 0 | O56: 0 | P56: 300 | Q56: 0 | R56: =+H56*20 -> 2.826 | S56: =SUM(I56:R56)*25% -> 78.88575 | T56: 1 | U56: =+SUM(I56:S56) -> 394.42875 | V56: =U56*T56 -> 394.42875
A57: 55 | B57: 9001797301 | C57: SUPPORT NON OVEN SIDE | D57: MS | E57: 125 | F57: 85 | G57: 6 | H57: =+E57*F57*G57*7.85/1000000 -> 0.5004375 | I57: =H57*90 -> 45.039375 | J57: 0 | K57: 0 | L57: 0 | M57: 0 | N57: 0 | O57: 0 | P57: 300 | Q57: 0 | R57: =+H57*20 -> 10.00875 | S57: =SUM(I57:R57)*25% -> 88.762031 | T57: 2 | U57: =+SUM(I57:S57) -> 443.81016 | V57: =U57*T57 -> 887.62031
A58: 56 | B58: 9001798901 | C58: VALVE MOUNTING PLATE MFH-1/4 | D58: MS | E58: 180 | F58: 100 | G58: 5 | H58: =+E58*F58*G58*7.85/1000000 -> 0.7065 | I58: =H58*90 -> 63.585 | J58: 0 | K58: 0 | L58: 0 | M58: 0 | N58: 0 | O58: 0 | P58: 350 | Q58: 0 | R58: =+H58*20 -> 14.13 | S58: =SUM(I58:R58)*25% -> 106.92875 | T58: 1 | U58: =+SUM(I58:S58) -> 534.64375 | V58: =U58*T58 -> 534.64375
A59: 57 | B59: 9001800101 | C59: VALVE MOUNTING PLATE MFH-1/4 -2VALVE | D59: MS | E59: 200 | F59: 100 | G59: 5 | H59: =+E59*F59*G59*7.85/1000000 -> 0.785 | I59: =H59*90 -> 70.65 | J59: 0 | K59: 0 | L59: 0 | M59: 0 | N59: 0 | O59: 0 | P59: 300 | Q59: 0 | R59: =+H59*20 -> 15.7 | S59: 0 | T59: 2 | U59: =+SUM(I59:S59) -> 386.35 | V59: =U59*T59 -> 772.7
A60: 58 | B60: 9001801101 | C60: SHAFT PIN ENCODER | D60: SS304 | E60: 25 | G60: 45 | H60: =+E60*E60*3.14/4*G60*8.55/1000000 -> 0.18876797 | I60: =H60*350 -> 66.068789 | J60: 180 | K60: 80 | L60: 0 | M60: 0 | N60: 0 | O60: 80 | P60: 0 | Q60: 0 | R60: 0 | S60: =SUM(I60:R60)*25% -> 101.5172 | T60: 2 | U60: =+SUM(I60:S60) -> 507.58599 | V60: =U60*T60 -> 1015.172
A61: 59 | B61: 9001801901 | C61: COUPLING ENCODER PIN | D61: SS304 | E61: 25 | G61: 40 | H61: =+E61*E61*3.14/4*G61*8.55/1000000 -> 0.16779375 | I61: =H61*350 -> 58.727812 | J61: 120 | K61: 80 | L61: 0 | M61: 0 | N61: 0 | O61: 80 | P61: 0 | Q61: 0 | R61: 0 | S61: =SUM(I61:R61)*25% -> 84.681953 | T61: 2 | U61: =+SUM(I61:S61) -> 423.40977 | V61: =U61*T61 -> 846.81953
A62: 60 | B62: 9001802001 | C62: ENCODER SPACER ROD | D62: MS | E62: 12 | G62: 60 | H62: =+E62*E62*3.14/4*G62*7.85/1000000 -> 0.05324184 | I62: =H62*90 -> 4.7917656 | J62: 120 | K62: 80 | L62: 0 | M62: 0 | N62: 15 | O62: 0 | P62: 0 | Q62: 0 | R62: =+H62*25 -> 1.331046 | S62: =SUM(I62:R62)*25% -> 55.280703 | T62: 6 | U62: =+SUM(I62:S62) -> 276.40351 | V62: =U62*T62 -> 1658.4211
A63: 61 | B63: 9001802701 | C63: BRACKET FOR MOUNTING LR 1/4 D MINI | D63: MS | E63: 200 | F63: 100 | G63: 3 | H63: =+E63*F63*G63*7.85/1000000 -> 0.471 | I63: =H63*90 -> 42.39 | J63: 0 | K63: 0 | L63: 0 | M63: 0 | N63: 0 | O63: 0 | P63: 300 | Q63: 0 | R63: =+H63*25 -> 11.775 | S63: =SUM(I63:R63)*25% -> 88.54125 | T63: 8 | U63: =+SUM(I63:S63) -> 442.70625 | V63: =U63*T63 -> 3541.65
A64: 62 | B64: 9001806501 | C64: WHISKER SWITCH MTG.PLATE FOR 1_4N INDEX. | D64: MS | E64: 190 | F64: 35 | G64: 8 | H64: =+E64*F64*G64*7.85/1000000 -> 0.41762 | I64: =H64*90 -> 37.5858 | J64: 0 | K64: 160 | L64: 0 | M64: 40 | N64: 30 | O64: 0 | P64: 0 | Q64: 0 | R64: =+H64*25 -> 10.4405 | S64: =SUM(I64:R64)*25% -> 69.506575 | T64: 4 | U64: =+SUM(I64:S64) -> 347.53287 | V64: =U64*T64 -> 1390.1315
A65: 63 | B65: 9001808401 | C65: PLATE ON BOTTLE DETECT LIMIT SWITCH | D65: MS | E65: 140 | F65: 50 | G65: 1 | H65: =+E65*F65*G65*7.85/1000000 -> 0.05495 | I65: =H65*90 -> 4.9455 | J65: 0 | K65: 0 | L65: 0 | M65: 0 | N65: 0 | O65: 0 | P65: 80 | Q65: 0 | R65: 0 | S65: =SUM(I65:R65)*25% -> 21.236375 | T65: 1 | U65: =+SUM(I65:S65) -> 106.18187 | V65: =U65*T65 -> 106.18187
A66: 64 | B66: 9001809301 | C66: BRACKET FOR MTG FRL ON FRAME | D66: MS | E66: =90+50 -> 140 | F66: 35 | G66: 3 | H66: =+E66*F66*G66*7.85/1000000 -> 0.115395 | I66: =H66*90 -> 10.38555 | J66: 0 | K66: 0 | L66: 0 | M66: 0 | N66: 40 | O66: 0 | P66: 300 | Q66: 0 | R66: 0 | S66: =SUM(I66:R66)*25% -> 87.596388 | T66: 2 | U66: =+SUM(I66:S66) -> 437.98194 | V66: =U66*T66 -> 875.96388
A67: 65 | B67: 9001809501 | C67: BRACKET FOR FRL MTG 2 | D67: MS | E67: 100 | F67: 100 | G67: 3 | H67: =+E67*F67*G67*7.85/1000000 -> 0.2355 | I67: =H67*90 -> 21.195 | J67: 0 | K67: 0 | L67: 0 | M67: 0 | N67: 0 | O67: 0 | P67: 160 | Q67: 0 | R67: 0 | S67: =SUM(I67:R67)*25% -> 45.29875 | T67: 2 | U67: =+SUM(I67:S67) -> 226.49375 | V67: =U67*T67 -> 452.9875
A68: 66 | B68: 9001811001 | C68: ADAPTER FOR SMC ZHV-10 VENTURI | D68: ALU 6082 | E68: 25 | G68: 40 | H68: =+E68*E68*3.14/4*G68*2.77/1000000 -> 0.05436125 | I68: =H68*450 -> 24.462563 | J68: 100 | K68: 80 | M68: 0 | N68: 15 | O68: 0 | P68: 0 | Q68: 0 | R68: 0 | S68: =SUM(I68:R68)*25% -> 54.865641 | T68: 6 | U68: =+SUM(I68:S68) -> 274.3282 | V68: =U68*T68 -> 1645.9692
A69: 67 | B69: 9001813201 | C69: SHAFT ASSEMBLY FOR DRVS | E69: 0 | F69: 0 | G69: 0 | H69: =+E69*F69*G69*7.85/1000000 -> 0 | I69: =H69*Z68 -> 0 | J69: 0 | K69: 0 | L69: 0 | M69: 0 | N69: 0 | O69: 0 | P69: 0 | Q69: 0 | R69: 0 | S69: =SUM(I69:R69)*25% -> 0 | T69: 6 | U69: =+SUM(I69:S69) -> 0 | V69: =U69*T69 -> 0 | W69: REGRATE
A70: 68 | B70: 9001816401 | C70: BLOCK HEATER MTG. BOTTOM | D70: ALU 6060 | E70: 85 | F70: 50 | G70: 16 | H70: =+E70*F70*G70*2.77/1000000 -> 0.18836 | I70: =H70*450 -> 84.762 | J70: 0 | K70: 200 | L70: 400 | M70: =6*20 -> 120 | N70: =4*15 -> 60 | O70: 0 | P70: 0 | Q70: 0 | R70: =+H70*150 -> 28.254 | S70: =SUM(I70:R70)*25% -> 223.254 | T70: 2 | U70: =+SUM(I70:S70) -> 1116.27 | V70: =U70*T70 -> 2232.54
A71: 69 | B71: 9001816501 | C71: BLOCK HEATER MTG. BOTTOM CENTER | D71: ALU 6060 | E71: 85 | F71: 85 | G71: 16 | H71: =+E71*F71*G71*2.77/1000000 -> 0.320212 | I71: =H71*450 -> 144.0954 | J71: 0 | K71: 200 | L71: 400 | M71: =10*20 -> 200 | N71: =14*15 -> 210 | O71: 0 | P71: 0 | Q71: 0 | R71: =+H71*150 -> 48.0318 | S71: =SUM(I71:R71)*25% -> 300.5318 | T71: 4 | U71: =+SUM(I71:S71) -> 1502.659 | V71: =U71*T71 -> 6010.636
A72: 70 | B72: 9001816601 | C72: BRACKET | D72: ALU 6060 | E72: 20 | F72: 20 | G72: 40 | H72: =+E72*F72*G72*2.77/1000000 -> 0.04432 | I72: =H72*450 -> 19.944 | J72: 0 | K72: 120 | L72: 0 | M72: 0 | N72: 0 | O72: 0 | P72: 0 | Q72: 0 | R72: 0 | S72: =SUM(I72:R72)*25% -> 34.986 | T72: 8 | U72: =+SUM(I72:S72) -> 174.93 | V72: =U72*T72 -> 1399.44
A73: 71 | B73: 9001816701 | C73: BRACKET | D73: ALU 6060 | E73: 20 | F73: 20 | G73: 70 | H73: =+E73*F73*G73*2.77/1000000 -> 0.07756 | I73: =H73*450 -> 34.902 | J73: 0 | K73: 150 | L73: 0 | M73: 0 | N73: 0 | O73: 0 | P73: 0 | Q73: 0 | R73: 0 | S73: =SUM(I73:R73)*25% -> 46.2255 | T73: 8 | U73: =+SUM(I73:S73) -> 231.1275 | V73: =U73*T73 -> 1849.02
A74: 72 | B74: 9001816901 | C74: BLOCK HEATER MTG. BOTTOM LEFT | D74: ALU 6060 | E74: 85 | F74: 50 | G74: 16 | H74: =+E74*F74*G74*2.77/1000000 -> 0.18836 | I74: =H74*450 -> 84.762 | J74: 0 | K74: 200 | L74: 400 | M74: =6*20 -> 120 | N74: =4*15 -> 60 | O74: 0 | P74: 0 | Q74: 0 | R74: =+H74*150 -> 28.254 | S74: =SUM(I74:R74)*25% -> 223.254 | T74: 2 | U74: =+SUM(I74:S74) -> 1116.27 | V74: =U74*T74 -> 2232.54
A75: 73 | B75: 9001817201 | C75: CLAMPING BKT FOR SICA CABLE TRAY | D75: MS | E75: 140 | F75: 30 | G75: 2 | H75: =+E75*F75*G75*7.85/1000000 -> 0.06594 | I75: =H75*90 -> 5.9346 | J75: 0 | K75: 0 | L75: 0 | M75: 0 | N75: 0 | O75: 0 | P75: 150 | Q75: 0 | R75: 10 | S75: =SUM(I75:R75)*25% -> 41.48365 | T75: 24 | U75: =+SUM(I75:S75) -> 207.41825 | V75: =U75*T75 -> 4978.038
A76: 74 | B76: 9001823901 | C76: QUARTZ BAR MOUNTING CLAMP | D76: SS304 | E76: 60 | F76: 20 | G76: 0.6 | H76: =+E76*F76*G76*8.55/1000000 -> 0.006156 | I76: =H76*350 -> 2.1546 | J76: 0 | K76: 0 | L76: 0 | M76: 0 | N76: 0 | O76: 0 | P76: 120 | Q76: 0 | R76: 10 | S76: =SUM(I76:R76)*25% -> 33.03865 | T76: 24 | U76: =+SUM(I76:S76) -> 165.19325 | V76: =U76*T76 -> 3964.638 | X76: OLD RATE
A77: 75 | B77: 9001827001 | C77: SHIM FOR STOPPER BLOCK 0.4 MM | D77: MS | E77: 55 | F77: 20 | G77: 0.4 | H77: =+E77*F77*G77*7.85/1000000 -> 0.003454 | I77: =H77*90 -> 0.31086 | J77: 0 | K77: 0 | L77: 0 | M77: 0 | N77: 0 | O77: 0 | P77: 80 | Q77: 0 | R77: 1 | S77: =SUM(I77:R77)*25% -> 20.327715 | T77: 88 | U77: =+SUM(I77:S77) -> 101.63858 | V77: =U77*T77 -> 8944.1946
A78: 76 | B78: 9001827701 | C78: SHIM FOR STOPPER BLOCK 0.2 MM | D78: MS | E78: 55 | F78: 20 | G78: 0.4 | H78: =+E78*F78*G78*7.85/1000000 -> 0.003454 | I78: =H78*90 -> 0.31086 | J78: 0 | K78: 0 | L78: 0 | M78: 0 | N78: 0 | O78: 0 | P78: 80 | Q78: 0 | R78: 1 | S78: =SUM(I78:R78)*25% -> 20.327715 | T78: 36 | U78: =+SUM(I78:S78) -> 101.63858 | V78: =U78*T78 -> 3658.9887
A79: 77 | B79: 9001832601 | C79: HOT NECK COLLER GUIDE | D79: SS304 | E79: 340 | F79: 245 | G79: 12 | H79: =+E79*F79*G79*8.55/1000000 -> 8.54658 | I79: =H79*350 -> 2991.303 | J79: 0 | K79: 550 | L79: 1600 | M79: 0 | N79: 40 | O79: 0 | P79: 0 | Q79: 0 | R79: 150 | S79: =SUM(I79:R79)*25% -> 1332.8257 | T79: 1 | U79: =+SUM(I79:S79) -> 6664.1287 | V79: =U79*T79 -> 6664.1287
A80: 78 | B80: 9001835301 | C80: BOTTLE OUTFEED NECK GUIDE PLATE_V25 | E80: 0 | F80: 0 | G80: 0 | H80: =+E80*F80*G80*7.85/1000000 -> 0 | I80: =H80*Z79 -> 0 | J80: 0 | K80: 0 | L80: 0 | M80: 0 | N80: 0 | O80: 0 | P80: 0 | Q80: 0 | R80: 0 | S80: =SUM(I80:R80)*25% -> 0 | T80: 1 | U80: 19629 | V80: =U80*T80 -> 19629 | X80: OLD RATE
A81: 79 | B81: 9001837501 | C81: PLATE FRONT COVER CENTRE FOR PILLAR | D81: ALU 6060 | E81: 180 | F81: 70 | G81: 8 | H81: =+E81*F81*G81*2.77/1000000 -> 0.279216 | I81: =H81*450 -> 125.6472 | J81: 0 | K81: 160 | L81: 300 | M81: 0 | N81: =20*20 -> 400 | O81: 0 | P81: 0 | Q81: 0 | R81: =+H81*150 -> 41.8824 | S81: =SUM(I81:R81)*25% -> 256.8824 | T81: 4 | U81: =+SUM(I81:S81) -> 1284.412 | V81: =U81*T81 -> 5137.648
A82: 80 | B82: 9001842201 | C82: CLAMP FOR 6MM PIPE | D82: MS | E82: 50 | F82: 20 | G82: 2 | H82: =+E82*F82*G82*7.85/1000000 -> 0.0157 | I82: =H82*90 -> 1.413 | J82: 0 | K82: 0 | L82: 0 | M82: 0 | N82: 0 | O82: 0 | P82: 50 | Q82: 0 | R82: 1 | S82: =SUM(I82:R82)*25% -> 13.10325 | T82: 18 | U82: =+SUM(I82:S82) -> 65.51625 | V82: =U82*T82 -> 1179.2925
A83: 81 | B83: 9001844301 | C83: HOPPER CAP COLLECTING | E83: 0 | F83: 0 | G83: 0 | H83: =+E83*F83*G83*7.85/1000000 -> 0 | I83: =H83*Z82 -> 0 | J83: 0 | K83: 0 | L83: 0 | M83: 0 | N83: 0 | O83: 0 | P83: 0 | Q83: 0 | R83: 0 | S83: =SUM(I83:R83)*25% -> 0 | T83: 3 | U83: =+SUM(I83:S83) -> 0 | V83: =U83*T83 -> 0 | W83: REGRATE
A84: 82 | B84: 9001846901 | C84: TUBE OD 6MM, LG 5M | D84: PNEUMATIC TUBE | E84: 6 | F84: 6 | G84: 5000 | H84: =+E84*F84*G84*1.77/1000000 -> 0.3186 | I84: =+H84*5000 -> 1593 | J84: 0 | K84: 0 | L84: 0 | M84: 0 | N84: 0 | O84: 0 | P84: 0 | Q84: 0 | R84: 0 | S84: =SUM(I84:R84)*25% -> 398.25 | T84: 3 | U84: =+SUM(I84:S84) -> 1991.25 | V84: =U84*T84 -> 5973.75
A85: 83 | B85: 9001852401 | C85: NECK GUIDE COLLAR SUPPORT | D85: POLYETHYLENE | E85: 100 | F85: 200 | G85: 12 | H85: =+E85*F85*G85*1.77/1000000 -> 0.4248 | I85: =H85*700 -> 297.36 | J85: 0 | K85: 200 | L85: 400 | M85: 0 | N85: 0 | O85: 0 | P85: 0 | Q85: 0 | R85: 0 | S85: =SUM(I85:R85)*25% -> 224.34 | T85: 2 | U85: =+SUM(I85:S85) -> 1121.7 | V85: =U85*T85 -> 2243.4
A86: 84 | B86: 9001852901 | C86: NECK GUIDE COLLAR SUPPORT-S.S | D86: SS304 | E86: 100 | F86: 200 | G86: 12 | H86: =+E86*F86*G86*8.55/1000000 -> 2.052 | I86: =H86*350 -> 718.2 | J86: 0 | K86: 350 | L86: 800 | M86: 0 | N86: 0 | O86: 300 | P86: 0 | Q86: 0 | R86: 150 | S86: =SUM(I86:R86)*25% -> 579.55 | T86: 2 | U86: =+SUM(I86:S86) -> 2897.75 | V86: =U86*T86 -> 5795.5 | X86: OLD RATE
A87: 85 | B87: 9001853001 | C87: RING FOR HOT PREFORM TOP HOLDING-S.S | T87: 8 | U87: 4878 | V87: =U87*T87 -> 39024 | X87: OLD RATE
A88: 86 | B88: 9001853201 | C88: RESTING PAD FOR FLAT BOTTLES-SR 5/2N | D88: ALU 7075 | E88: 705 | F88: 20 | G88: 20 | H88: =+E88*F88*G88*2.77/1000000 -> 0.78114 | I88: =H88*550 -> 429.627 | J88: 0 | K88: 0 | L88: 800 | M88: 0 | N88: 0 | O88: 0 | P88: 0 | Q88: 0 | R88: =+H88*150 -> 117.171 | S88: =SUM(I88:R88)*25% -> 336.6995 | T88: 1 | U88: =+SUM(I88:S88) -> 1683.4975 | V88: =U88*T88 -> 1683.4975
A89: 87 | B89: 9001854801 | C89: ROD | D89: MS | E89: 16 | G89: 450 | H89: =+E89*E89*3.14/4*G89*7.85/1000000 -> 0.7098912 | I89: =H89*350 -> 248.46192 | J89: 200 | K89: 0 | L89: 0 | M89: 0 | N89: 20 | O89: 0 | P89: 0 | Q89: 0 | R89: =+H89*25 -> 17.74728 | S89: =SUM(I89:R89)*25% -> 121.5523 | T89: 2 | U89: =+SUM(I89:S89) -> 607.7615 | V89: =U89*T89 -> 1215.523
A90: 88 | B90: 9001855001 | C90: PLATE FOR CYLINDER MTG SHUTTLE | D90: MS | E90: 75 | F90: 50 | G90: 14 | H90: =+E90*F90*G90*7.85/1000000 -> 0.412125 | I90: =H90*90 -> 37.09125 | J90: 0 | K90: 120 | L90: 200 | M90: =6*25 -> 150 | N90: 40 | O90: 0 | P90: 0 | Q90: 0 | R90: =+H90*25 -> 10.303125 | S90: =SUM(I90:R90)*25% -> 139.34859 | T90: 6 | U90: =+SUM(I90:S90) -> 696.74297 | V90: =U90*T90 -> 4180.4578
A91: 89 | B91: 9001855301 | C91: STOPPER NYLON SHUTTLE 27.5MM | D91: NYLON06 | E91: 55 | F91: 35 | G91: 16 | H91: =+E91*F91*G91*1.77/1000000 -> 0.054516 | I91: =H91*690 -> 37.61604 | J91: 0 | K91: 120 | L91: 0 | M91: =4*20 -> 80 | N91: 0 | O91: 0 | P91: 0 | Q91: 0 | R91: 0 | S91: =SUM(I91:R91)*25% -> 59.40401 | T91: 6 | U91: =+SUM(I91:S91) -> 297.02005 | V91: =U91*T91 -> 1782.1203
A92: 90 | B92: 9001856401 | C92: STOPPER SHUTTLE 19MM | D92: NYLON06 | E92: 55 | F92: 35 | G92: 16 | H92: =+E92*F92*G92*1.77/1000000 -> 0.054516 | I92: =H92*690 -> 37.61604 | J92: 0 | K92: 120 | L92: 0 | M92: =4*20 -> 80 | N92: 0 | O92: 0 | P92: 0 | Q92: 0 | R92: 0 | S92: =SUM(I92:R92)*25% -> 59.40401 | T92: 6 | U92: =+SUM(I92:S92) -> 297.02005 | V92: =U92*T92 -> 1782.1203
A93: 91 | B93: 9001856501 | C93: MOUNTING PLATE FOR W BRACKET GATE 1 | D93: MS | E93: 0 | F93: 0 | G93: 0 | H93: =+E93*F93*G93*7.85/1000000 -> 0 | I93: =H93*350 -> 0 | J93: 0 | K93: 0 | L93: 0 | M93: 0 | N93: 0 | O93: 0 | P93: 0 | Q93: 0 | R93: 0 | S93: =SUM(I93:R93)*25% -> 0 | T93: 6 | U93: 920 | V93: =U93*T93 -> 5520 | X93: OLD RATE
A94: 92 | B94: 9001856601 | C94: MOUNTING PLATE FOR AUTO LUBRICATION | D94: MS | E94: 300 | F94: 250 | G94: 6 | H94: =+E94*F94*G94*7.85/1000000 -> 3.5325 | I94: =H94*90 -> 317.925 | J94: 0 | K94: 0 | L94: 0 | M94: 0 | N94: 0 | O94: 0 | P94: 600 | Q94: 0 | R94: =+H94*25 -> 88.3125 | S94: =SUM(I94:R94)*25% -> 251.55937 | T94: 5 | U94: =+SUM(I94:S94) -> 1257.7969 | V94: =U94*T94 -> 6288.9844
A95: 93 | B95: 9001856701 | C95: BASE PLATE FOR ELECTRICAL INDEXING | T95: 2 | U95: 7358 | V95: =U95*T95 -> 14716 | X95: OLD RATE
A96: 94 | B96: 9001857501 | C96: INDEX 1 UNIT MTG. SIDE PLATE | T96: 4 | U96: 1126 | V96: =U96*T96 -> 4504 | X96: OLD RATE
A97: 95 | B97: 9001857601 | C97: TIE-BAR HOLDING BLOCK | T97: 8 | U97: 407 | V97: =U97*T97 -> 3256 | X97: OLD RATE
A98: 96 | B98: 9001857801 | C98: PUSHER CLAPPER INDEX 1 | D98: MS | E98: 255 | F98: 135 | G98: 14 | H98: =+E98*F98*G98*7.85/1000000 -> 3.7833075 | I98: =H98*90 -> 340.49767 | J98: 0 | K98: 450 | L98: 600 | M98: 0 | N98: 0 | O98: 150 | P98: 0 | Q98: 0 | R98: =+H98*25 -> 94.582687 | S98: =SUM(I98:R98)*25% -> 408.77009 | T98: 2 | U98: =+SUM(I98:S98) -> 2043.8505 | V98: =U98*T98 -> 4087.7009
A99: 97 | B99: 9001857901 | C99: PUSHER NYLON HOLDER | T99: 2 | U99: 476 | V99: =U99*T99 -> 952 | X99: OLD RATE
A100: 98 | B100: 9001859001 | C100: PIPE T JOIN FOR HYDRA | T100: 1 | U100: =+SUM(I100:S100) -> 0 | V100: =U100*T100 -> 0 | W100: REGRATE
A101: 99 | B101: 9001861001 | C101: STRETCHING ROD GUIDE BUDH-SR_5/2 | D101: POLYETHYLENE | E101: 55 | G101: 70 | H101: =+E101*E101*3.14/4*G101*1.77/1000000 -> 0.29421604 | I101: =H101*700 -> 205.95123 | J101: 400 | K101: 0 | L101: 0 | M101: 40 | N101: 0 | O101: 0 | P101: 0 | Q101: 0 | R101: 0 | S101: =SUM(I101:R101)*25% -> 161.48781 | T101: 2 | U101: =+SUM(I101:S101) -> 807.43903 | V101: =U101*T101 -> 1614.8781
...

Sheet 22
A1: Sr No | B1: Drawing No. | C1: Description | D1: Material | E1: Material Size | H1: Wight | I1: Material Cost
A2: 1 | B2: 9000734304 | D2: ms | E2: 220 | F2: 230 | G2: 20 | H2: =+E2*F2*G2*7.85/1000000 -> 7.9442 | I2: =H2*90 -> 714.978
A3: 2 | B3: 9000734304 | D3: ms | E3: 325 | F3: 200 | G3: 16 | H3: =+E3*F3*G3*7.85/1000000 -> 8.164 | I3: =H3*90 -> 734.76
A4: 3 | B4: 9000734304 | D4: ms | E4: 325 | F4: 200 | G4: 16 | H4: =+E4*F4*G4*7.85/1000000 -> 8.164 | I4: =H4*90 -> 734.76
A5: 4 | B5: 9000734304 | D5: ms | E5: 80 | F5: 120 | G5: 16 | H5: =+E5*F5*G5*7.85/1000000 -> 1.20576 | I5: =H5*90 -> 108.5184
A6: 5 | B6: 9000734304 | D6: ms | E6: 45 | F6: 70 | G6: 25 | H6: =+E6*F6*G6*7.85/1000000 -> 0.6181875 | I6: =H6*90 -> 55.636875
A7: 7 | B7: 9000734304 | D7: ms | E7: 365 | G7: 20 | H7: =+E7*E7*3.14/4*G7*8/1000000 -> 16.73306 | I7: =H7*90 -> 1505.9754
H8: =SUM(H2:H7) -> 42.829207 | I8: =SUM(I2:I7) -> 3854.6287

Sheet 25
A1: Sr No | B1: Drawing No. | C1: Description | D1: Material | E1: Material Size | H1: Wight | I1: Material Cost
A2: 1 | B2: 9000745203 | D2: MS | E2: 225 | F2: 110 | G2: 20 | H2: =+E2*F2*G2*7.85/1000000 -> 3.88575 | I2: =H2*90 -> 349.7175
A3: 2 | B3: 9000745203 | E3: 185 | F3: 110 | G3: 30 | H3: =+E3*F3*G3*7.85/1000000 -> 4.792425 | I3: =H3*90 -> 431.31825
A4: 3 | B4: 9000745203 | E4: 55 | F4: 100 | G4: 16 | H4: =+E4*F4*G4*7.85/1000000 -> 0.6908 | I4: =H4*90 -> 62.172

Sheet 29
A1: Sr No | B1: Drawing No. | C1: Description | D1: Material | E1: Material Size | H1: Wight | I1: Material Cost
A2: 1 | B2: 9000745203 | D2: ss | E2: 310 | F2: 120 | G2: 25 | H2: =+E2*F2*G2*7.85/1000000 -> 7.3005 | I2: =H2*90 -> 657.045
A3: 2 | B3: 9000745203 | D3: ss | E3: 130 | F3: 85 | G3: 12 | H3: =+E3*F3*G3*7.85/1000000 -> 1.04091 | I3: =H3*90 -> 93.6819
A4: 3 | B4: 9000745203 | D4: ss | E4: 35 | F4: 85 | G4: 12 | H4: =+E4*F4*G4*7.85/1000000 -> 0.280245 | I4: =H4*90 -> 25.22205

Sheet 62
A1: Sr No | B1: Drawing No. | C1: Description | D1: Material | E1: Material Size | H1: Wight | I1: Material Cost
A2: 1 | B2: 9000745203 | D2: ss | E2: 110 | F2: 40 | G2: 8 | H2: =+E2*F2*G2*7.85/1000000 -> 0.27632 | I2: =H2*90 -> 24.8688
A3: 2 | B3: 9000745203 | D3: ss | E3: 100 | F3: 40 | G3: 8 | H3: =+E3*F3*G3*7.85/1000000 -> 0.2512 | I3: =H3*90 -> 22.608

Sheet SHEET 3
B3: Material | C3: Short Text | D3: Qty
B4: 9000011003 | C4: COOLING RAIL SUPPORT PLATE ( | D4: 16
B5: 9000011103 | C5: COOLING RAIL SUPPORT PLATE ( | D5: 8
B6: 9000118001 | C6: SPACER FOR AIR COLLECTOR 40 RUBIN (0425@ | D6: 8
B7: 9000152202 | C7: 1/2N CLAMP UNIT PINION HOLDING BLOCK | D7: 1
B8: 9000166101 | C8: CENTER HEATER STAND COVER TOP SIDE | D8: 1
B9: 9000182703 | C9: SPRING FOR CLAMP UNIT FOR 1/4N | D9: 16
B10: 9000184102 | C10: CYLINDER EXTENSION FOR SLIDING PLATE | D10: 8
B11: 9000197803 | C11: TIE BAR LOCKING | D11: 8
B12: 9000229001 | C12: EJECTOR JAW HOLDING PLATE | D12: 24
B13: 9000234902 | C13: SPACER FOR NORGREN VALVE MTG.BRACKET | D13: 4
B14: 9000236502 | C14: BLOW PIN BUSH SR 1/2 | D14: 4
B15: 9000392401 | C15: BOLT FOR LOADER TIE BAR | D15: 14
... B106: 9001861501 | C106: BUSH (SPIDER)_12.7_SR 5/2 | D106: 2
